Metadata-Version: 2.4
Name: mytestlib-1
Version: 1.0.0
Summary: My Test Library.
Home-page: https://pypi.org/manage/projects/
Author: Yosuke Saka
Author-email: yosuke.saka3416@gmail.com
Dynamic: author
Dynamic: author-email
Dynamic: home-page
Dynamic: summary
